Metadata-Version: 1.0
Name: distributions-rayed-wahed
Version: 0.1
Summary: Gaussian Distributions
Home-page: UNKNOWN
Author: UNKNOWN
Author-email: UNKNOWN
License: UNKNOWN
Platform: UNKNOWN
